pixqrcode/__init__.py
pixqrcode/model/__init__.py
pixqrcode/model/merchant_account.py
pixqrcode/model/pix.py
pixqrcode/model/pix_error.py
pixqrcode/service/__init__.py
pixqrcode/service/generate_code.py
pixqrcode/service/key_identify.py
pixqrcode/service/validate_pix.py
pixqrcode/utils/__init__.py
pixqrcode/utils/crc16.py
pixqrcode/utils/format_values.py
pixqrcode-1.1.0.dist-info/METADATA
pixqrcode-1.1.0.dist-info/WHEEL
pixqrcode-1.1.0.dist-info/top_level.txt
pixqrcode-1.1.0.dist-info/RECORD
