Metadata-Version: 2.1
Name: pixqrcode
Version: 1.1.0
Summary: QRCode Pix for python
Home-page: 
Author: Joao Carlos
Author-email: joao-mostela@hotmail.com
Requires-Dist: qrcode
